LICENSE
MANIFEST.in
README.rst
setup.py
bin/js-zipcode.py
jsreport/__init__.py
jsreport.egg-info/PKG-INFO
jsreport.egg-info/SOURCES.txt
jsreport.egg-info/dependency_links.txt
jsreport.egg-info/not-zip-safe
jsreport.egg-info/requires.txt
jsreport.egg-info/top_level.txt