Metadata-Version: 1.1
Name: jsreport
Version: 0.2.5
Summary: Simple tool to pull basic reporting data out of JustServe (https://www.justserve.org/).
Home-page: https://github.com/abadstubner/JustServe_Reports
Author: abadstubner
Author-email: andrew+pypi@badstubner.com
License: MIT
Platform: UNKNOWN
Classifier: Development Status :: 4 - Beta
Classifier: Environment :: Console
Classifier: Intended Audience :: Religion
Classifier: Intended Audience :: Other Audience
Classifier: License :: OSI Approved :: MIT License
Classifier: Natural Language :: English
Classifier: Operating System :: OS Independent
Classifier: Programming Language :: Python :: 2.7
Classifier: Topic :: Other/Nonlisted Topic
